spark_batch/__init__.py
spark_batch/run.py
spark_batch/data/shp/BML_BADM_AS.dbf
spark_batch/data/shp/BML_BADM_AS.prj
spark_batch/data/shp/BML_BADM_AS.sbn
spark_batch/data/shp/BML_BADM_AS.sbx
spark_batch/data/shp/BML_BADM_AS.shp
spark_batch/data/shp/BML_BADM_AS.shp.xml
spark_batch/data/shp/BML_BADM_AS.shx
spark_batch/data/shp/BML_HADM_AS.dbf
spark_batch/data/shp/BML_HADM_AS.prj
spark_batch/data/shp/BML_HADM_AS.sbn
spark_batch/data/shp/BML_HADM_AS.sbx
spark_batch/data/shp/BML_HADM_AS.shp
spark_batch/data/shp/BML_HADM_AS.shp.xml
spark_batch/data/shp/BML_HADM_AS.shx
spark_batch/data/shp2024/BML_BADM_AS.dbf
spark_batch/data/shp2024/BML_BADM_AS.prj
spark_batch/data/shp2024/BML_BADM_AS.sbn
spark_batch/data/shp2024/BML_BADM_AS.sbx
spark_batch/data/shp2024/BML_BADM_AS.shp
spark_batch/data/shp2024/BML_BADM_AS.shx
spark_batch/data/shp2024/BML_HADM_AS.dbf
spark_batch/data/shp2024/BML_HADM_AS.sbn
spark_batch/data/shp2024/BML_HADM_AS.sbx
spark_batch/data/shp2024/BML_HADM_AS.shp
spark_batch/data/shp2024/BML_HADM_AS.shp.xml
spark_batch/data/shp2024/BML_HADM_AS.shx
spark_batch/lib/__init__.py
spark_batch/lib/csv_table_manager.py
spark_batch/lib/delta_table_manager.py
spark_batch/lib/elt_manager.py
spark_batch/lib/json_table_manager.py
spark_batch/lib/mariadb_table_manager.py
spark_batch/lib/oracle_table_manager.py
spark_batch/lib/postgresql_table_manager.py
spark_batch/lib/pxlogger.py
spark_batch/lib/resource_manager.py
spark_batch/lib/spark_session.py
spark_batch/lib/udf_aes_cipher.py
spark_batch/lib/udf_geo_converter.py
spark_batch/lib/util.py
spark_batch-2.7.dist-info/METADATA
spark_batch-2.7.dist-info/WHEEL
spark_batch-2.7.dist-info/top_level.txt
spark_batch-2.7.dist-info/RECORD
