Metadata-Version: 2.1
Name: spark-batch
Version: 2.7
Summary: spark_delta_batch for bronze > silve > gold > mart auto
Home-page: UNKNOWN
Author: GunSik Choi
Author-email: cgshome@gmail.com
License: UNKNOWN
Platform: UNKNOWN
Requires-Dist: pyyaml
Requires-Dist: psycopg2-binary
Requires-Dist: delta-spark
Requires-Dist: boto3
Requires-Dist: pycryptodome
Requires-Dist: geopandas
